mudus/__init__.py
mudus/__main__.py
mudus/database/__init__.py
mudus/database/accumulate.py
mudus/database/directory_sizes.py
mudus/database/lazy_loading.py
mudus/database/mudus_database.py
mudus/database/scan_with_scandir.py
mudus/scan/__init__.py
mudus/scan/mudus_scan_non_interactive.py
mudus/scan/mudus_scan_screen.py
mudus/scan/mudus_scan_status.py
mudus/view/__init__.py
mudus/view/mudus_loading_indicator.py
mudus/view/mudus_view_screen.py
mudus/view/mudus_view_table.py
mudus-1.0.0.dist-info/METADATA
mudus-1.0.0.dist-info/WHEEL
mudus-1.0.0.dist-info/entry_points.txt
mudus-1.0.0.dist-info/licenses/LICENSE
mudus-1.0.0.dist-info/RECORD
