Metadata-Version: 2.4
Name: mudus
Version: 1.0.0
Summary: Multi-User Disk USage scanner and reporter. Quickly figure out where a specific user has left files on a shared disk by showing cumulative (recursive) directory sizes and letting the user drill down in a file-explorer like Textual TUI showing only their files.
Project-URL: Homepage, https://github.com/TormodLandet/mudus
Project-URL: Source, https://github.com/TormodLandet/mudus
Author-email: Tormod Landet <tormod@landet.net>
License-Expression: Apache-2.0
License-File: LICENSE
Keywords: disk-space,disk-usage,hpc,python,storage,textual,textualize
Classifier: Development Status :: 5 - Production/Stable
Classifier: License :: OSI Approved :: Apache Software License
Classifier: Programming Language :: Python :: 3
Requires-Python: >=3.10
Requires-Dist: textual>=5.0
